pysnobal/__init__.py
pysnobal/cli.py
pysnobal/ipysnobal.py
pysnobal/pysnobal.py
pysnobal/pysnobal_core_config.ini
pysnobal/utils.py
pysnobal/core/__init__.py
pysnobal/core/constants.py
pysnobal/point/__init__.py
pysnobal/point/input.py
pysnobal/point/libsnobal.py
pysnobal/point/snobal.py
pysnobal/point/snow_state.py
pysnobal/spatial/__init__.py
pysnobal/spatial/isnobal.py
pysnobal/tests/__init__.py
pysnobal/tests/pysnobal_config.ini
pysnobal/tests/test_pysnobal.py
pysnobal/tests/point/__init__.py
pysnobal/tests/point/test_input.py
pysnobal/tests/point/test_snow_state.py
pysnobal/tests/point/test_turbulent_transfer.py
pysnobal/tests/test_data_point/gold_csv/config.ini
pysnobal/tests/test_data_point/gold_csv/gold.pysnobal.csv
pysnobal/tests/test_data_point/gold_csv/gold.snobal.data.input.csv
pysnobal/tests/test_data_point/gold_csv/gold.snobal.data.input.short.csv
pysnobal/tests/test_data_point/gold_ipw/README.md
pysnobal/tests/test_data_point/gold_ipw/gold.inheight.input
pysnobal/tests/test_data_point/gold_ipw/gold.snobal.data.input
pysnobal/tests/test_data_point/gold_ipw/gold.snobal.data.input.short
pysnobal/tests/test_data_point/gold_ipw/gold.snobal.out
pysnobal/tests/test_data_point/gold_ipw/gold.snobal.out.all
pysnobal/tests/test_data_point/gold_ipw/gold.snobal.ppt.input
pysnobal/tests/test_data_point/gold_ipw/gold.snow.properties.input
pysnobal/tests/test_data_point/gold_ipw/run_snobal.sh
pysnobal/tests/test_data_point/libsnobal/gold_turbulent_transfer.csv
pysnobal-0.2.3.dist-info/AUTHORS.md
pysnobal-0.2.3.dist-info/LICENSE
pysnobal-0.2.3.dist-info/METADATA
pysnobal-0.2.3.dist-info/WHEEL
pysnobal-0.2.3.dist-info/entry_points.txt
pysnobal-0.2.3.dist-info/top_level.txt
pysnobal-0.2.3.dist-info/RECORD
